MANIFEST.in
README.txt
setup.py
docs/COPYRIGHT.txt
docs/HISTORY.txt
docs/LICENSE.txt
src/cromlech/__init__.py
src/cromlech.sqlalchemy.egg-info/PKG-INFO
src/cromlech.sqlalchemy.egg-info/SOURCES.txt
src/cromlech.sqlalchemy.egg-info/dependency_links.txt
src/cromlech.sqlalchemy.egg-info/entry_points.txt
src/cromlech.sqlalchemy.egg-info/namespace_packages.txt
src/cromlech.sqlalchemy.egg-info/not-zip-safe
src/cromlech.sqlalchemy.egg-info/requires.txt
src/cromlech.sqlalchemy.egg-info/top_level.txt
src/cromlech/sqlalchemy/__init__.py
src/cromlech/sqlalchemy/components.py
src/cromlech/sqlalchemy/controlled.py
src/cromlech/sqlalchemy/test_api.txt