Metadata-Version: 1.1
Name: cromlech.sqlalchemy
Version: 0.4
Summary: Cromlech Web Framework utility methods and components for applications based on SQLAlchemy.
Home-page: http://gitweb.dolmen-project.org
Author: Dolmen Team
Author-email: dolmen@list.dolmen-project.org
License: ZPL
Keywords: SQLAlchemy ORM Cromlech
Platform: UNKNOWN
Classifier: Programming Language :: Python
